README.md
setup.py
Pysion/Engine.py
Pysion/__init__.py
Pysion.egg-info/PKG-INFO
Pysion.egg-info/SOURCES.txt
Pysion.egg-info/dependency_links.txt
Pysion.egg-info/top_level.txt