Metadata-Version: 2.1
Name: Pysion
Version: 0.0.1
Summary: EasyVision inferencing API
Author: Joel Lach
